{"sections":{"main":{"type":"main-page","settings":{"padding-top":40,"padding-bottom":40,"padding-top-1429":50,"padding-bottom-1429":50,"padding-top-1199":45,"padding-bottom-1199":45,"padding-top-991":40,"padding-bottom-991":40,"padding-top-767":35,"padding-bottom-767":35,"padding-top-575":30,"padding-bottom-575":30}},"177672015470975dd7":{"type":"_blocks","blocks":{"ai_gen_block_a7ad872_GyQYf4":{"type":"ai_gen_block_a7ad872","name":"Custom Text Equipment","settings":{"container_width":1200,"content_alignment":"center","element_spacing":30,"section_bg_color":"#052b3e","section_padding_top":50,"section_padding_bottom":30,"section_padding_horizontal":20,"text_box_1_content":"<h2>Commercial Laundry Equipment for Sale<\/h2><h2> in BC, Alberta, and the Yukon<\/h2>","text_box_1_alignment":"center","text_box_1_color":"#c6a228","text_box_1_size":32,"show_text_box_2":true,"text_box_2_content":"<p>Bichin Laundry Equipment supplies <strong>commercial laundry equipment<\/strong> for BC, Alberta, and Yukon laundromats and On-Premise laundry operations that need reliable, high-performance machines built for serious daily laundry room use. <\/p><p><br\/>We help <strong>laundromat owners (<\/strong>as well as operators in <strong>hospitality, healthcare, care facilities, multi-housing, fitness, and other high-volume laundry environments)<\/strong> choose equipment that fits their workflow, utility setup, capacity needs, and long-term business goals.<\/p>","text_box_2_alignment":"center","text_box_2_color":"#ffffff","text_box_2_size":18,"show_text_box_3":false,"text_box_3_content":"<p>Additional text content goes here<\/p>","text_box_3_alignment":"center","text_box_3_color":"#ffffff","text_box_3_size":18,"image_position":3,"image_max_width":800,"image_border_radius":0,"show_button":true,"button_text":"Shop now","button_link":"shopify:\/\/collections\/on-premise-laundry-equipment","button_alignment":"center","button_bg_color":"#c6a228","button_text_color":"#ffffff","button_hover_bg_color":"#052b3e","button_hover_text_color":"#ffffff","button_border_color":"#c6a228","button_hover_border_color":"#ffffff","button_border_width":0,"button_border_radius":0,"button_font_size":16,"button_font_weight":500,"button_padding_vertical":15,"button_padding_horizontal":30},"blocks":{}}},"block_order":["ai_gen_block_a7ad872_GyQYf4"],"settings":{}},"category_collection_style1_w7zfjE":{"type":"category-collection-style1","blocks":{"collection_7JCAtd":{"type":"collection","settings":{"image":"shopify:\/\/shop_images\/Dexter_Softmount_Washer_Extractor.png","height_ratio":"137","title":"On-Premise Machines","collection":"on-premise-laundry-equipment","category1":"Category","category1_link":"","category2":"Category","category2_link":"","category3":"Category","category3_link":"","category4":"Category","category4_link":"","category5":"Category","category5_link":""}},"collection_39GRA4":{"type":"collection","settings":{"image":"shopify:\/\/shop_images\/Laundromat_full_of_dexter_equipment.jpg","height_ratio":"137","title":"Vended Machines","collection":"","category1":"Category","category1_link":"","category2":"Category","category2_link":"","category3":"Category","category3_link":"","category4":"Category","category4_link":"","category5":"Category","category5_link":""}},"collection_Rb97af":{"type":"collection","settings":{"height_ratio":"137","title":"Flatwork Ironers","collection":"","category1":"Category","category1_link":"","category2":"Category","category2_link":"","category3":"Category","category3_link":"","category4":"Category","category4_link":"","category5":"Category","category5_link":""}}},"block_order":["collection_7JCAtd","collection_39GRA4","collection_Rb97af"],"name":"Category section style1","settings":{"section_width":"full_width","collection_position":"horizontal-position","main_subheading":"Commercial Laundry Equipment For Sale","main_heading":"Commercial Washers, Dryers & Flatwork Ironers","main_paragraph":"On-Premise & Vended Commercial & Industrial Laundry Machines for Sale","text_alignment":"center","collection-desktop":3,"collection-large-tablet":3,"collection-tablet":3,"collection-mobile":2,"autoplay-enable":true,"arrows":true,"dots":false,"speed":"600","loop":true,"bg_color":"#ffffff","theme_heading_color":"#08364c","theme_subheading_color":"#be9722","content_color":"#000000","collection_bg":"#ffffff","collection-name-color":"#333333","subcategory-name-color":"#666666","collection-name-hover-color":"#ffffff","padding-top":40,"padding-bottom":40,"padding-top-1429":70,"padding-bottom-1429":70,"padding-top-1199":60,"padding-bottom-1199":60,"padding-top-991":50,"padding-bottom-991":50,"padding-top-767":40,"padding-bottom-767":40,"padding-top-575":30,"padding-bottom-575":30,"margin-top":0,"margin-bottom":0,"margin-top-1429":0,"margin-bottom-1429":0,"margin-top-1199":0,"margin-bottom-1199":0,"margin-top-991":0,"margin-bottom-991":0,"margin-top-767":0,"margin-bottom-767":0,"margin-top-575":0,"margin-bottom-575":0}},"1776728157fbe80a6c":{"type":"_blocks","settings":{}},"1776721677e48e5c2e":{"type":"_blocks","settings":{}},"177672426903bc940e":{"type":"_blocks","settings":{}},"1776729227a477ad2e":{"type":"_blocks","blocks":{"ai_gen_block_1894b3c_dG6gaU":{"type":"ai_gen_block_1894b3c","name":"Custom coded text gradient","settings":{"section_padding":40,"max_width":1200,"spacing_between_items":0,"text_box_padding":30,"text_box_border_radius":8,"text_box_image_border_radius":8,"text_box_1_enabled":true,"text_box_1_content":"<h2>Commercial Laundry Equipment That Works as Hard as You Do<\/h2>","text_box_1_position":1,"text_box_1_alignment":"center","text_box_1_font_size":32,"text_box_1_color":"#08364c","text_box_1_show_image":false,"text_box_2_enabled":true,"text_box_2_content":"<p>When you run a laundromat or manage an on-premise laundry room, equipment performance affects everything — customer experience, staff efficiency, utility costs, throughput, and downtime. Bichin Laundry Equipment supplies <strong>Dexter heavy-duty commercial laundry machines<\/strong> and <strong>Huebsch Small Chassis washers and dryers <\/strong>designed to process large loads, handle repeated use, and deliver dependable results in demanding environments.<\/p><p><strong><br\/>We work with customers who are:<\/strong><\/p><p>⦿ Opening a new laundromat<\/p><p>⦿ Retooling or upgrading an existing laundromat<\/p><p>⦿ Replacing aging commercial washers or dryers<\/p><p>⦿ Expanding a hotel, healthcare, or care home laundry room<\/p><p>⦿ Building a more efficient on-premise laundry setup<\/p><p><br\/>We currently sell a variety of capacities for <strong>Dexter OPL (On-Premise Laundry) hardmount washers, softmount washers, single dryers, stacked dryers, and washer-dryer stackers. <\/strong>To figure out which OPL machines will work well with your business operations and the space (and infrastructure) you have available, check out our current selection of Dexter OPL machines and then get in touch so we can help you get the right machine for the job.<\/p><p><\/p>","text_box_2_position":2,"text_box_2_alignment":"left","text_box_2_font_size":18,"text_box_2_color":"#333333","text_box_2_show_image":false,"text_box_3_enabled":true,"text_box_3_content":"<h3><strong>Vended Commercial Washers<\/strong><\/h3><p>Vended commercial washing machines are built for constant use in self-serve laundry environments. They need to be durable, efficient, and easy for customers to operate. We sell a wide variety of Dexter vended washing machines—large capacity hard and soft mount—and Huebsch small chassis machines. <\/p>","text_box_3_position":3,"text_box_3_alignment":"left","text_box_3_font_size":16,"text_box_3_color":"#333333","text_box_3_show_image":true,"text_box_3_image":"shopify:\/\/shop_images\/dexter_vended_machines.jpg","text_box_4_enabled":true,"text_box_4_content":"<h3><strong>Vended Commercial Tumble Dryers<\/strong><\/h3><p>Vended commercial dryers need to keep pace with (or, better yet, keep one step ahead of) washer volume while drying efficiently, and helping reduce wait times for customers. Our selection of vended Dexter tumble dryers cover a wide array of situations, from high capacity, quick turnaround to small stackers that fit in tight spaces but still get the job done quickly.<\/p>","text_box_4_position":4,"text_box_4_alignment":"left","text_box_4_font_size":16,"text_box_4_color":"#333333","text_box_4_show_image":true,"text_box_4_image":"shopify:\/\/shop_images\/Img_0898.jpg","text_box_5_enabled":true,"text_box_5_content":"<h3><strong>Stack Washer-Dryer and Stack Dryer Units<\/strong><\/h3><p>If maximizing floor space matters, stack equipment can help increase capacity without expanding your footprint. Stacked commercial laundry equipment works in a large variety of spaces and configurations, so it’s often a good solution for laundromats (and other laundry facilities that need to fit a lot of machines into a small space).<\/p><p>We currently offer <strong>stacked dryers and washer-dryer stackers <\/strong>for sale, with capacities ranging from smaller commercial sizes to large-capacity laundromat equipment.<\/p>","text_box_5_position":5,"text_box_5_alignment":"left","text_box_5_font_size":16,"text_box_5_color":"#333333","text_box_5_show_image":true,"text_box_5_image":"shopify:\/\/shop_images\/group-img-1099-12i-copy.jpg","text_box_6_enabled":false,"text_box_6_content":"","text_box_6_position":6,"text_box_6_alignment":"left","text_box_6_font_size":16,"text_box_6_color":"#333333","text_box_6_show_image":false,"text_box_7_enabled":false,"text_box_7_content":"","text_box_7_position":7,"text_box_7_alignment":"center","text_box_7_font_size":16,"text_box_7_color":"#333333","text_box_7_show_image":false,"text_box_8_enabled":false,"text_box_8_content":"","text_box_8_position":8,"text_box_8_alignment":"center","text_box_8_font_size":16,"text_box_8_color":"#333333","text_box_8_show_image":false,"text_box_9_enabled":false,"text_box_9_content":"","text_box_9_position":9,"text_box_9_alignment":"center","text_box_9_font_size":16,"text_box_9_color":"#333333","text_box_9_show_image":false,"text_box_10_enabled":false,"text_box_10_content":"","text_box_10_position":10,"text_box_10_alignment":"center","text_box_10_font_size":16,"text_box_10_color":"#333333","text_box_10_show_image":false,"show_image":false,"image_position":5,"image_border_radius":8,"show_button":false,"button_text":"Learn more","button_link":"","button_alignment":"center","button_font_size":16,"button_font_weight":"500","button_padding_vertical":12,"button_padding_horizontal":30,"button_bg_color":"#c6a228","button_text_color":"#ffffff","button_hover_bg_color":"#052b3e","button_hover_text_color":"#ffffff","button_border_width":0,"button_border_color":"#c6a228","button_hover_border_color":"#052b3e","button_border_radius":4},"blocks":{}},"ai_gen_block_1894b3c_TjNfKc":{"type":"ai_gen_block_1894b3c","name":"Custom coded text gradient","settings":{"section_padding":40,"max_width":1200,"spacing_between_items":0,"text_box_padding":30,"text_box_border_radius":8,"text_box_image_border_radius":8,"text_box_1_enabled":true,"text_box_1_content":"<h3>Huebsch Small Chassis Machines<br\/> for Compact Commercial Laundry Rooms<\/h3>","text_box_1_position":1,"text_box_1_alignment":"center","text_box_1_font_size":32,"text_box_1_color":"#08364c","text_box_1_show_image":false,"text_box_1_image":"shopify:\/\/shop_images\/Huebsch_Small_Chassis_light_commercial.png","text_box_2_enabled":true,"text_box_2_content":"<p>Not every commercial laundry room has the space for a full-size equipment layout. That is where Huebsch Small Chassis (aka light commercial laundry) machines can be a smart fit. Bichin Laundry Equipment now offers these compact commercial laundry solutions for customers who need dependable performance in a smaller footprint.<\/p><p>Huebsch Small Chassis machines are a strong option for apartment buildings, multi-housing laundry rooms, hotels, care facilities, staff laundry rooms, and other on-premise laundry environments where space is limited but durability and performance still matter. They are also a practical choice for smaller laundry rooms that need to make the most of available square footage without sacrificing commercial-grade equipment.<\/p><p>These machines are designed to help businesses maximize laundry capacity while keeping the layout efficient and functional. For property owners and operators, that can mean better use of the room, easier replacement planning, and a more practical equipment solution for tighter spaces.<\/p>","text_box_2_position":2,"text_box_2_alignment":"left","text_box_2_font_size":18,"text_box_2_color":"#333333","text_box_2_show_image":true,"text_box_2_image":"shopify:\/\/shop_images\/Huebsch_Small_Chassis_light_commercial.png","text_box_3_enabled":true,"text_box_3_content":"<h3><strong>Why do Huebsch Light Commercial Laundry Machines Appeal to Commercial Laundry Operators?<\/strong><\/h3><p><br\/><strong>Compact equipment can be the right answer when:<\/strong><\/p><p>🧺 Floor space is limited<\/p><p>🧺  A side-by-side washer and dryer setup is not ideal<\/p><p>🧺 You want to improve layout efficiency<\/p><p>🧺 You need commercial-grade performance in a smaller laundry room<\/p><p>🧺 You are upgrading an older shared laundry area or on-premise laundry space<br\/><br\/><\/p><p>Huebsch Small Chassis machines give customers another option when a standard equipment footprint is not the best fit for the building or the laundry room design.<\/p><p><strong><br\/>Huebsch Laundry Machines are a Good Fit for Space-Conscious Laundry Setups<\/strong><\/p><p>For businesses and property managers trying to balance performance, reliability, and available square footage, Huebsch Small Chassis machines can help create a more efficient laundry setup. They are especially useful in buildings and facilities where laundry demand is steady, but room size is limited.<\/p><p>By adding Huebsch Small Chassis machines to our equipment offering, Bichin Laundry Equipment is now able to help more customers find a commercial laundry solution that matches both your operational needs and your available physical space.<\/p>","text_box_3_position":3,"text_box_3_alignment":"left","text_box_3_font_size":20,"text_box_3_color":"#333333","text_box_3_show_image":false,"text_box_4_enabled":false,"text_box_4_content":"","text_box_4_position":4,"text_box_4_alignment":"left","text_box_4_font_size":16,"text_box_4_color":"#333333","text_box_4_show_image":false,"text_box_5_enabled":false,"text_box_5_content":"","text_box_5_position":5,"text_box_5_alignment":"left","text_box_5_font_size":16,"text_box_5_color":"#333333","text_box_5_show_image":false,"text_box_6_enabled":false,"text_box_6_content":"","text_box_6_position":6,"text_box_6_alignment":"left","text_box_6_font_size":16,"text_box_6_color":"#333333","text_box_6_show_image":false,"text_box_7_enabled":false,"text_box_7_content":"","text_box_7_position":7,"text_box_7_alignment":"center","text_box_7_font_size":16,"text_box_7_color":"#333333","text_box_7_show_image":false,"text_box_8_enabled":false,"text_box_8_content":"","text_box_8_position":8,"text_box_8_alignment":"center","text_box_8_font_size":16,"text_box_8_color":"#333333","text_box_8_show_image":false,"text_box_9_enabled":false,"text_box_9_content":"","text_box_9_position":9,"text_box_9_alignment":"center","text_box_9_font_size":16,"text_box_9_color":"#333333","text_box_9_show_image":false,"text_box_10_enabled":false,"text_box_10_content":"","text_box_10_position":10,"text_box_10_alignment":"center","text_box_10_font_size":16,"text_box_10_color":"#333333","text_box_10_show_image":false,"show_image":false,"image_position":5,"image_border_radius":8,"show_button":false,"button_text":"Learn more","button_link":"","button_alignment":"center","button_font_size":16,"button_font_weight":"500","button_padding_vertical":12,"button_padding_horizontal":30,"button_bg_color":"#c6a228","button_text_color":"#ffffff","button_hover_bg_color":"#052b3e","button_hover_text_color":"#ffffff","button_border_width":0,"button_border_color":"#c6a228","button_hover_border_color":"#052b3e","button_border_radius":4},"blocks":{}}},"block_order":["ai_gen_block_1894b3c_dG6gaU","ai_gen_block_1894b3c_TjNfKc"],"settings":{}},"1778536921de8ca656":{"type":"_blocks","settings":{}},"1780528829f5ff8e75":{"type":"_blocks","blocks":{"ai_gen_block_cbe10ce_TVhbnb":{"type":"ai_gen_block_cbe10ce","name":"Custom Code 3 with buttons","settings":{"max_width":1200,"desktop_width_percent":100,"section_padding_top":50,"section_padding_bottom":50,"spacing_between_items":30,"default_text_color":"#333333","show_image":false,"image_position":0,"text_box_1_enabled":true,"text_box_1_content":"<h3>Specialty Laundry Equipment and Additional Solutions<\/h3>","text_box_1_heading_level":"p","text_box_1_font_size":16,"text_box_1_text_color":"#333333","text_box_1_alignment":"center","text_box_1_position":1,"text_box_1_show_image":true,"text_box_1_show_button":true,"text_box_1_button_text":"Learn more","text_box_1_button_link":"shopify:\/\/pages\/contact-us","text_box_2_enabled":true,"text_box_2_content":"<p>Some operations need more than standard commercial washers and dryers. We currently sell speciality laundry equipment for many different types of laundry operations, such as:<\/p><p>🧺 Flatwork Ironers <\/p><p>🧺 Cabinet dryers<\/p><p>🧺 Wet and dry cleaning models<\/p><p>🧺 Industrial equipment<\/p><p>🧺 Laundry carts<\/p><p>🧺 Related commercial laundry support products, such as parts and chemicals<\/p>","text_box_2_heading_level":"p","text_box_2_font_size":16,"text_box_2_text_color":"#08364c","text_box_2_alignment":"left","text_box_2_position":2,"text_box_2_show_image":false,"text_box_2_show_button":false,"text_box_2_button_text":"Learn more","text_box_2_button_link":"","text_box_3_enabled":false,"text_box_3_content":"<p>Add your rich text content here<\/p>","text_box_3_heading_level":"p","text_box_3_font_size":16,"text_box_3_text_color":"#333333","text_box_3_alignment":"center","text_box_3_position":3,"text_box_3_show_image":false,"text_box_3_show_button":false,"text_box_3_button_text":"Learn more","text_box_3_button_link":"","text_box_4_enabled":false,"text_box_4_content":"<p>Add your rich text content here<\/p>","text_box_4_heading_level":"p","text_box_4_font_size":16,"text_box_4_text_color":"#333333","text_box_4_alignment":"center","text_box_4_position":4,"text_box_4_show_image":false,"text_box_4_show_button":false,"text_box_4_button_text":"Learn more","text_box_4_button_link":"","text_box_5_enabled":false,"text_box_5_content":"<p>Add your rich text content here<\/p>","text_box_5_heading_level":"p","text_box_5_font_size":16,"text_box_5_text_color":"#333333","text_box_5_alignment":"center","text_box_5_position":5,"text_box_5_show_image":false,"text_box_5_show_button":false,"text_box_5_button_text":"Learn more","text_box_5_button_link":"","text_box_6_enabled":false,"text_box_6_content":"<p>Add your rich text content here<\/p>","text_box_6_heading_level":"p","text_box_6_font_size":16,"text_box_6_text_color":"#333333","text_box_6_alignment":"center","text_box_6_position":6,"text_box_6_show_image":false,"text_box_6_show_button":false,"text_box_6_button_text":"Learn more","text_box_6_button_link":"","text_box_7_enabled":false,"text_box_7_content":"<p>Add your rich text content here<\/p>","text_box_7_heading_level":"p","text_box_7_font_size":16,"text_box_7_text_color":"#333333","text_box_7_alignment":"center","text_box_7_position":7,"text_box_7_show_image":false,"text_box_7_show_button":false,"text_box_7_button_text":"Learn more","text_box_7_button_link":"","text_box_8_enabled":false,"text_box_8_content":"<p>Add your rich text content here<\/p>","text_box_8_heading_level":"p","text_box_8_font_size":16,"text_box_8_text_color":"#333333","text_box_8_alignment":"center","text_box_8_position":8,"text_box_8_show_image":false,"text_box_8_show_button":false,"text_box_8_button_text":"Learn more","text_box_8_button_link":"","text_box_9_enabled":false,"text_box_9_content":"<p>Add your rich text content here<\/p>","text_box_9_heading_level":"p","text_box_9_font_size":16,"text_box_9_text_color":"#333333","text_box_9_alignment":"center","text_box_9_position":9,"text_box_9_show_image":false,"text_box_9_show_button":false,"text_box_9_button_text":"Learn more","text_box_9_button_link":"","text_box_10_enabled":false,"text_box_10_content":"<p>Add your rich text content here<\/p>","text_box_10_heading_level":"p","text_box_10_font_size":16,"text_box_10_text_color":"#333333","text_box_10_alignment":"center","text_box_10_position":10,"text_box_10_show_image":false,"text_box_10_show_button":false,"text_box_10_button_text":"Learn more","text_box_10_button_link":"","button_padding_vertical":12,"button_padding_horizontal":24,"button_bg_color":"#c6a228","button_text_color":"#ffffff","button_hover_bg_color":"#be9722","button_hover_text_color":"#ffffff","button_font_size":16,"button_font_weight":500,"button_border_radius":4,"button_border_width":0,"button_border_color":"#c6a228","button_hover_border_color":"#be9722","show_bottom_button":false,"bottom_button_text":"Shop now","bottom_button_link":"","bottom_button_alignment":"center","bottom_button_margin_top":30,"bottom_button_padding_vertical":14,"bottom_button_padding_horizontal":32,"bottom_button_bg_color":"#c6a228","bottom_button_text_color":"#ffffff","bottom_button_hover_bg_color":"#be9722","bottom_button_hover_text_color":"#ffffff","bottom_button_font_size":18,"bottom_button_font_weight":600,"bottom_button_border_radius":4,"bottom_button_border_width":0,"bottom_button_border_color":"#c6a228","bottom_button_hover_border_color":"#be9722"},"blocks":{}}},"block_order":["ai_gen_block_cbe10ce_TVhbnb"],"settings":{}},"17805309863eb0c6e6":{"type":"_blocks","blocks":{"ai_gen_block_387c332_GhNaR6":{"type":"ai_gen_block_387c332","settings":{"heading":"Frequently Asked Questions About Commercial Laundry Equipment","desktop_width_percent":100,"background_color":"#052b3e","divider_color":"#c6a228","heading_font":"system_ui_n4","heading_color":"#c6a228","question_font":"system_ui_n4","question_color":"#ffffff","question_hover_color":"#c6a228","icon_color":"#c6a228","answer_font":"system_ui_n4","answer_color":"#ffffff","link_color":"#c6a228","link_hover_color":"#be9722","question_1":"Can Bichin Laundry Equipment help me choose the right commercial laundry equipment mix for our laundry operations?","answer_1":"<p>Yes, absolutely! Commercial laundry equipment should be matched to your actual operation — not just your wish list.<\/p><p>The Bichin Laundry Equipment team helps customers think through:<\/p><ul><li>Available square footage<\/li><li>Laundry volume<\/li><li>Peak usage times<\/li><li>Linen or load types<\/li><li>Utility access and installation requirements<\/li><li>Revenue goals<\/li><li>Capacity mix<\/li><li>Workflow efficiency<\/li><li>Future growth<br\/><\/li><\/ul><p>We are here to support you through the entire commercial equipment buying process—layout planning, store design, equipment selection, financing assistance, ordering, installation, programming, demonstration, and ongoing service and maintenance.<\/p>","link_text_1":"We're here to make this experience easier for you, get in touch today!","link_url_1":"shopify:\/\/pages\/contact-us","question_2":"Why do laundry businesses choose to work with Bichin Laundry Equipment? ","answer_2":"<p>Bichin Laundry Equipment is more than a catalog of commercial laundry machines for sale. We work hard to go the extra mile for every customer by providing wide-reaching support in all areas of sales, installations, service, parts, and troubleshooting. Being an <strong>authorized supplier and distributor<\/strong> of Dexter and Huebsch commercial laundry equipment means we are trusted by the manufacturers and our machines are supported by warranties, service, planning help, and ongoing customer care. <\/p><p>We will never “set it and forget it” when you hire us. We are in it for the long haul and we will be here to support you with:<\/p><ul><li>Equipment selection<\/li><li>Laundromat planning<\/li><li>Layout guidance<\/li><li>Installation coordination<\/li><li>Parts access<\/li><li>Maintenance and service<br\/><br\/><\/li><\/ul>","link_text_2":"","link_url_2":"","question_3":"What types of commercial laundry equipment does Bichin Laundry Equipment sell?","answer_3":"<p>Bichin Laundry Equipment supplies Dexter and Huebsch commercial washers, dryers, stack units, on-premise laundry equipment, and other commercial laundry solutions for laundromats and high-volume laundry operations.<\/p>","link_text_3":"","link_url_3":"","question_4":"Does Bichin Laundry Equipment sell equipment for laundromats?","answer_4":"<p>Yes. Laundromats are a major focus, and Bichin Laundry Equipment’s current core customers are laundromat owners. We help with planning, design, equipment selection, installation, and ongoing support for laundromat owners throughout BC, Alberta, and the Yukon.<\/p>","link_text_4":"","link_url_4":"","question_5":"Does Bichin Laundry Equipment also supply equipment for hotels and healthcare facilities?","answer_5":"<p>Yes. Bichin Laundry Equipment currently offers commercial laundry equipment sales for businesses beyond laundromats, including including hotels, healthcare environments, and other businesses with large laundry operations, both vended and On-Premise.<\/p>","link_text_5":"","link_url_5":"","question_6":"Can Bichin Laundry Equipment help me with selecting the right equipment mix?","answer_6":"<p>Yes. Bichin Laundry Equipment’s main mandate is to provide owners and operators of large laundry operations with help designing floor plans, machine mix, quantities, installation, and ongoing support.<\/p>","link_text_6":"","link_url_6":"","question_7":"What brands does Bichin Laundry Equipment carry?","answer_7":"<p>Bichin Laundry Equipment currently offers commercial laundry equipment from <strong>Dexter<\/strong> (both hardmount and softmount models) and Wascomat, as well as small chassis laundry equipment made by Huebsch.<\/p>","link_text_7":"","link_url_7":"","question_8":"Do you offer compact commercial laundry machines for smaller laundry rooms?","answer_8":"<p>Yes. Bichin Laundry Equipment now offers <strong>Huebsch Small Chassis machines<\/strong> for customers who need commercial laundry performance in a smaller footprint. These machines are a strong fit for apartment buildings, hotels, care facilities, staff laundry rooms, and other on-premise laundry spaces where floor space is limited but dependable commercial equipment is still important.<\/p>","link_text_8":"","link_url_8":"","question_9":"","answer_9":"","link_text_9":"","link_url_9":"","question_10":"","answer_10":"","link_text_10":"","link_url_10":""},"blocks":{}}},"block_order":["ai_gen_block_387c332_GhNaR6"],"settings":{}}},"order":["main","177672015470975dd7","category_collection_style1_w7zfjE","1776728157fbe80a6c","1776721677e48e5c2e","177672426903bc940e","1776729227a477ad2e","1778536921de8ca656","1780528829f5ff8e75","17805309863eb0c6e6"]}